nailfold_image_enhance/__init__.py
nailfold_image_enhance/config.py
nailfold_image_enhance/core.py
nailfold_image_enhance/exceptions.py
nailfold_image_enhance/image_processor.py
nailfold_image_enhance/utils.py
nailfold_image_enhance/video_processor.py
Nailfold_enhance-1.0.2.dist-info/LICENSE.txt
Nailfold_enhance-1.0.2.dist-info/METADATA
Nailfold_enhance-1.0.2.dist-info/WHEEL
Nailfold_enhance-1.0.2.dist-info/top_level.txt
Nailfold_enhance-1.0.2.dist-info/RECORD
