Metadata-Version: 2.1
Name: Nailfold-enhance
Version: 1.0.2
Summary: Nailfold images and videos enhance
Author: ZhouBin_FOSU
Author-email: wuyanxiong@fosu.edu.cn
License: MIT
Classifier: Development Status :: 4 - Beta
Classifier: Intended Audience :: Healthcare Industry
Classifier: Intended Audience :: Developers
Classifier: License :: OSI Approved :: MIT License
Classifier: Programming Language :: Python :: 3
Classifier: Programming Language :: Python :: 3.8
Classifier: Programming Language :: Python :: 3.9
Classifier: Programming Language :: Python :: 3.10
Classifier: Topic :: Scientific/Engineering :: Image Processing
Classifier: Topic :: Multimedia :: Video :: Conversion
Requires-Python: >=3.7
License-File: LICENSE.txt
Requires-Dist: opencv-python >=4.8.0
Requires-Dist: numpy >=1.21.0
Provides-Extra: dev
Requires-Dist: pytest >=7.0 ; extra == 'dev'
Requires-Dist: flake8 >=6.0 ; extra == 'dev'
Requires-Dist: sphinx >=6.2 ; extra == 'dev'
